royalflush/__init__.py
royalflush/cli.py
royalflush/_agent/__init__.py
royalflush/_agent/agent_factory.py
royalflush/_agent/base.py
royalflush/_agent/coordinator.py
royalflush/_agent/launcher.py
royalflush/_agent/observer.py
royalflush/_agent/premiofl/__init__.py
royalflush/_agent/premiofl/acol.py
royalflush/_agent/premiofl/macofl.py
royalflush/_agent/premiofl/pmacofl_max.py
royalflush/_agent/premiofl/pmacofl_min.py
royalflush/_behaviour/__init__.py
royalflush/_behaviour/coordination.py
royalflush/_behaviour/launcher.py
royalflush/_behaviour/observer.py
royalflush/_behaviour/premiofl/__init__.py
royalflush/_behaviour/premiofl/communication.py
royalflush/_behaviour/premiofl/consensus.py
royalflush/_behaviour/premiofl/fsm.py
royalflush/_behaviour/premiofl/layer_receiver.py
royalflush/_behaviour/premiofl/similarity_receiver.py
royalflush/_behaviour/premiofl/train.py
royalflush/_commands/__init__.py
royalflush/_commands/analyze_logs.py
royalflush/_commands/create_template.py
royalflush/_commands/run.py
royalflush/_commands/version.py
royalflush/agent/__init__.py
royalflush/agent/premiofl/__init__.py
royalflush/behaviour/__init__.py
royalflush/commands/__init__.py
royalflush/dataset/__init__.py
royalflush/dataset/cifar.py
royalflush/dataset/dataloader_generator.py
royalflush/dataset/mnist.py
royalflush/datatypes/__init__.py
royalflush/datatypes/consensus.py
royalflush/datatypes/consensus_manager.py
royalflush/datatypes/data.py
royalflush/datatypes/experiment.py
royalflush/datatypes/graph.py
royalflush/datatypes/metrics.py
royalflush/datatypes/models.py
royalflush/log/__init__.py
royalflush/log/algorithm.py
royalflush/log/csv.py
royalflush/log/data.py
royalflush/log/filter.py
royalflush/log/general.py
royalflush/log/log.py
royalflush/log/message.py
royalflush/log/nn.py
royalflush/message/__init__.py
royalflush/message/message.py
royalflush/message/multipart.py
royalflush/nn/__init__.py
royalflush/nn/model_factory.py
royalflush/nn/model/__init__.py
royalflush-0.4.1.dist-info/licenses/LICENSE
royalflush-0.4.1.dist-info/METADATA
royalflush-0.4.1.dist-info/WHEEL
royalflush-0.4.1.dist-info/entry_points.txt
royalflush-0.4.1.dist-info/top_level.txt
royalflush-0.4.1.dist-info/RECORD
